numbers_parser/__init__.py
numbers_parser/_cat_numbers.py
numbers_parser/_csv2numbers.py
numbers_parser/_unpack_numbers.py
numbers_parser/bullets.py
numbers_parser/cell.py
numbers_parser/constants.py
numbers_parser/containers.py
numbers_parser/currencies.py
numbers_parser/document.py
numbers_parser/exceptions.py
numbers_parser/experimental.py
numbers_parser/formula.py
numbers_parser/iwafile.py
numbers_parser/iwork.py
numbers_parser/model.py
numbers_parser/numbers_cache.py
numbers_parser/numbers_uuid.py
numbers_parser/roman.py
numbers_parser/tokenizer.py
numbers_parser/xrefs.py
numbers_parser/data/empty.numbers
numbers_parser/generated/TNArchives_pb2.py
numbers_parser/generated/TNArchives_sos_pb2.py
numbers_parser/generated/TNCommandArchives_pb2.py
numbers_parser/generated/TNCommandArchives_sos_pb2.py
numbers_parser/generated/TSAArchives_pb2.py
numbers_parser/generated/TSAArchives_sos_pb2.py
numbers_parser/generated/TSACommandArchives_sos_pb2.py
numbers_parser/generated/TSCEArchives_pb2.py
numbers_parser/generated/TSCH3DArchives_pb2.py
numbers_parser/generated/TSCHArchives_Common_pb2.py
numbers_parser/generated/TSCHArchives_GEN_pb2.py
numbers_parser/generated/TSCHArchives_pb2.py
numbers_parser/generated/TSCHArchives_sos_pb2.py
numbers_parser/generated/TSCHCommandArchives_pb2.py
numbers_parser/generated/TSCHPreUFFArchives_pb2.py
numbers_parser/generated/TSCKArchives_pb2.py
numbers_parser/generated/TSCKArchives_sos_pb2.py
numbers_parser/generated/TSDArchives_pb2.py
numbers_parser/generated/TSDArchives_sos_pb2.py
numbers_parser/generated/TSDCommandArchives_pb2.py
numbers_parser/generated/TSKArchives_pb2.py
numbers_parser/generated/TSPArchiveMessages_pb2.py
numbers_parser/generated/TSPDatabaseMessages_pb2.py
numbers_parser/generated/TSPMessages_pb2.py
numbers_parser/generated/TSSArchives_pb2.py
numbers_parser/generated/TSSArchives_sos_pb2.py
numbers_parser/generated/TSTArchives_pb2.py
numbers_parser/generated/TSTArchives_sos_pb2.py
numbers_parser-4.17.0.post1.dist-info/licenses/LICENSE.rst
numbers_parser-4.17.0.post1.dist-info/METADATA
numbers_parser-4.17.0.post1.dist-info/WHEEL
numbers_parser-4.17.0.post1.dist-info/entry_points.txt
numbers_parser-4.17.0.post1.dist-info/top_level.txt
numbers_parser-4.17.0.post1.dist-info/RECORD
