Metadata-Version: 2.4
Name: numbers-parser
Version: 4.17.0.post1
Summary: Read and write Apple Numbers spreadsheets
Author-email: Jon Connell <python@figsandfudge.com>
License-Expression: MIT
Project-URL: repository, https://github.com/masaccio/numbers-parser
Project-URL: documentation, https://github.com/masaccio/numbers-parser/blob/main/README.md
Classifier: Topic :: Office/Business :: Financial :: Spreadsheet
Classifier: Programming Language :: Python :: 3
Classifier: Operating System :: OS Independent
Requires-Python: >=3.10
License-File: LICENSE.rst
Requires-Dist: compact-json>=1.1.3
Requires-Dist: protobuf>=6.32.0
Requires-Dist: python-snappy>=0.7
Requires-Dist: sigfig>=1.3.3
Requires-Dist: setuptools>=70.0.0
Requires-Dist: importlib-resources>=6.1
Requires-Dist: enum-tools>=0.11
Requires-Dist: python-dateutil>=2.9.0.post0
Dynamic: license-file
